oolong/__init__.py
oolong-0.1.dist-info/DESCRIPTION.rst
oolong-0.1.dist-info/METADATA
oolong-0.1.dist-info/RECORD
oolong-0.1.dist-info/WHEEL
oolong-0.1.dist-info/metadata.json
oolong-0.1.dist-info/top_level.txt
