Metadata-Version: 2.0
Name: oolong
Version: 0.1
Summary: common tool
Home-page: UNKNOWN
Author: roc.zhao
Author-email: peng.zhao@tongji.edu.cn
License: MIT License
Keywords: daily tool,common code
Platform: any
Classifier: Development Status :: 3 - Alpha
Classifier: Intended Audience :: Developers
Classifier: Topic :: Software Development :: Libraries
Classifier: License :: OSI Approved :: MIT License
Classifier: Programming Language :: Python :: 2
Classifier: Programming Language :: Python :: 2.6
Classifier: Programming Language :: Python :: 2.7
